fdl/__init__.py
fdl/_factory.py
fdl/_main.py
fdl/_utils.py
fdl/_common/__init__.py
fdl/_common/dict_config.py
fdl/_common/log.py
fdl/_core/__init__.py
fdl/_core/command_gen.py
fdl/_core/command_run.py
fdl/_core/command_show.py
fdl/modules/__init__.py
fastDepsLoader-0.0.1.dist-info/LICENSE
fastDepsLoader-0.0.1.dist-info/METADATA
fastDepsLoader-0.0.1.dist-info/WHEEL
fastDepsLoader-0.0.1.dist-info/entry_points.txt
fastDepsLoader-0.0.1.dist-info/top_level.txt
fastDepsLoader-0.0.1.dist-info/RECORD
