Metadata-Version: 2.1
Name: fastDepsLoader
Version: 0.0.1
Summary: Fast Dependence Loader
License: Apache License
Project-URL: Homepage, https://github.com/lpdink/fdl
Project-URL: Repository, https://github.com/lpdink/fdl
Classifier: Programming Language :: Python :: 3
Classifier: License :: OSI Approved :: Apache Software License
Classifier: Operating System :: OS Independent
Requires-Python: >=3.6
License-File: LICENSE
